wavecount_cli/__init__.py
wavecount_cli/utils.py
wavecount_cli/version_check.py
wavecount_cli/wave.py
wavecount_cli/commands/__init__.py
wavecount_cli/commands/change_commands.py
wavecount_cli/commands/delete_commands.py
wavecount_cli/commands/failed_update_commands.py
wavecount_cli/commands/hash_command.py
wavecount_cli/commands/new_commands.py
wavecount_cli/commands/reboot_commands.py
wavecount_cli/commands/reset_command.py
wavecount_cli/commands/show_commands.py
wavecount_cli/commands/update_commands.py
wavecount_cli/services/__init__.py
wavecount_cli/services/backend_services.py
wavecount_cli-2.3.3.dist-info/LICENSE
wavecount_cli-2.3.3.dist-info/METADATA
wavecount_cli-2.3.3.dist-info/WHEEL
wavecount_cli-2.3.3.dist-info/entry_points.txt
wavecount_cli-2.3.3.dist-info/top_level.txt
wavecount_cli-2.3.3.dist-info/RECORD
