Metadata-Version: 2.1
Name: wavecount-cli
Version: 2.3.3
Summary: Wavecount cli
Author: Navid Ahrary
Author-email: N.Ahrary@domil.io
License: ISC
Classifier: Programming Language :: Python :: 3
Classifier: Environment :: Console
Classifier: License :: OSI Approved :: ISC License (ISCL)
Classifier: Operating System :: OS Independent
Requires-Python: >=3.6
License-File: LICENSE
Requires-Dist: requests
Requires-Dist: click
Requires-Dist: halo
Requires-Dist: pyfiglet
Requires-Dist: inquirer
Requires-Dist: pydash
